flask_view_counter.py
flask_view_counter-0.1.2.dist-info/LICENSE
flask_view_counter-0.1.2.dist-info/METADATA
flask_view_counter-0.1.2.dist-info/WHEEL
flask_view_counter-0.1.2.dist-info/top_level.txt
flask_view_counter-0.1.2.dist-info/RECORD
