Metadata-Version: 2.1
Name: flask-view-counter
Version: 0.1.2
Summary: Adds lightweight request metrics to flask applications
Home-page: https://gitlab.com/shiftlesscode/flask-view-counter/
Author: Shiftless
Author-email: shiftlesscode@gmail.com
License: WTFPL
Platform: any
Classifier: Environment :: Web Environment
Classifier: Framework :: Flask
Classifier: Development Status :: 3 - Alpha
Classifier: Intended Audience :: Developers
Classifier: Operating System :: OS Independent
Classifier: Programming Language :: Python :: 3
Classifier: Topic :: Internet :: WWW/HTTP :: Dynamic Content
Classifier: Topic :: Software Development :: Libraries :: Python Modules
Requires-Python: >=3.6
